foamclient/__init__.py
foamclient/redis_clients.py
foamclient/schema_registry.py
foamclient/serializer.py
foamclient/zmq_clients.py
foamclient/tests/__init__.py
foamclient/tests/conftest.py
foamclient/tests/test_redis_clients.py
foamclient/tests/test_serializer.py
foamclient/tests/test_zmq_clients.py
foamclient-0.2.0.dist-info/LICENSE
foamclient-0.2.0.dist-info/METADATA
foamclient-0.2.0.dist-info/WHEEL
foamclient-0.2.0.dist-info/top_level.txt
foamclient-0.2.0.dist-info/RECORD
