Metadata-Version: 2.1
Name: foamclient
Version: 0.2.0
Author-email: Jun Zhu <zhujun981661@gmail.com>
License: BSD 3-Clause License
Project-URL: repository, https://github.com/zhujun98/foamclient
Classifier: Development Status :: 4 - Beta
Classifier: Intended Audience :: Developers
Classifier: License :: OSI Approved :: BSD License
Classifier: Operating System :: OS Independent
Classifier: Programming Language :: Python :: 3.9
Classifier: Programming Language :: Python :: 3.10
Classifier: Topic :: Scientific/Engineering :: Information Analysis
Requires-Python: >=3.9
License-File: LICENSE
Requires-Dist: msgpack
Requires-Dist: numpy
Requires-Dist: pyzmq
Requires-Dist: hiredis
Requires-Dist: redis
Requires-Dist: fastavro >=1.8.2
Provides-Extra: test
Requires-Dist: pytest ; extra == 'test'
Requires-Dist: pytest-cov ; extra == 'test'
